{"name":"Semanticsdata","tagline":"Evaluation data for SEMANTICS 2015.","body":"##Dependencies\r\nIssue the following commands to install all needed packages in Ubuntu 14.04.\r\n\r\n        sudo apt-get install python-pip python-librdf ipython python-psutil\r\n\r\n        sudo pip install networkx\r\n\r\n##Dataset links\r\nThe 100% DBPEDIA dataset can be downloaded from the link below:\r\n* The 100% DBPEDIA dataset: http://benchmark.dbpedia.org/benchmark_100.nt.bz2\r\n\r\n##Summary Creation\r\n1. To create the RDF-type summary graph of a given N-Triples RDF dataset, execute the summary creation script:\r\n\r\n        create_summary.py benchmark_x.nt\r\nwhere benchmark_x.nt is the input dataset.\r\n\r\n##Shortest Paths Algorithm\r\nAn implementation of the shortest paths algorithm presented in the paper is available in the file ksp.py.\r\n\r\n##Path-to-SPARQL Converter\r\nThe file converter.py contains an implementation of the path-to-SPARQL converter.\r\n\r\n","google":"","note":"Don't delete this file! It's used internally to help with page regeneration."}